setup.py
text2speech/__init__.py
text2speech/bus.py
text2speech/ssml.py
text2speech/util.py
text2speech/visimes.py
text2speech.egg-info/PKG-INFO
text2speech.egg-info/SOURCES.txt
text2speech.egg-info/dependency_links.txt
text2speech.egg-info/entry_points.txt
text2speech.egg-info/requires.txt
text2speech.egg-info/top_level.txt
text2speech/modules/__init__.py
text2speech/modules/espeak_tts.py
text2speech/modules/espeakng_tts.py
text2speech/modules/festival_tts.py
text2speech/modules/google_tts.py
text2speech/modules/ibm_tts.py
text2speech/modules/mary_tts.py
text2speech/modules/mbrola_tts.py
text2speech/modules/mimic2_tts.py
text2speech/modules/mimic_tts.py
text2speech/modules/mozilla_tts.py
text2speech/modules/pico_tts.py
text2speech/modules/polly_tts.py
text2speech/modules/responsive_voice_tts.py
text2speech/modules/spdsay_tts.py
text2speech/modules/voice_rss.py