Metadata-Version: 1.0
Name: text2speech
Version: 0.1.8
Summary: TTS engines
Home-page: https://github.com/HelloChatterbox/text2speech
Author: jarbasAI
Author-email: jarbasai@mailfence.com
License: apache
Platform: UNKNOWN
